{"originalTitle": "\u00c1smundar_Saga_Kappabana_Chapter_4", "author": "Not Available", "sourceLink": "http://www.perseus.tufts.edu/hopper/opensource/download", "source": "Perseus", "language": "Old_Norse", "englishTitle": "\u00c1smundar_Saga_Kappabana_Chapter_4", "text": {"0": "N\u00fa er \u00fear til m\u00e1ls at taka, er Hildibrandr er, br\u00f3\u00f0irhans, sonr Helga konungs, en Helgi konungr fell \u00edherna\u00f0i. Hildibrandr braut undir sik mikinn afla oksveima\u00f0i v\u00ed\u00f0a me\u00f0 her sinn. Hann var m\u00e6g\u00f0r vi\u00f0 \u00feannkonung, er Lazinus h\u00e9t. Hann var einn inn r\u00edkasti konungr.Hann s\u00f3tti \u00feangat me\u00f0 vinganaror\u00f0um til m\u00e1gss\u00edns, ok var honum \u00fear vel fagnat. Hann t\u00f3k n\u00fa atgerast framgjarn mj\u00f6k, er aflinn \u00f3x. \u00de\u00e1 v\u00e1ru hertugarg\u00f6fgir ok \u00e6ttst\u00f3rir \u00ed Saxlandi. Hildibrandr H\u00fanakappif\u00f3r n\u00fa \u00e1 hendr \u00feeim ok kva\u00f0st vilja, at \u00feeir ger\u00f0i honumsl\u00edka vir\u00f0ing sem hann beiddi e\u00f0a \u00feeir mundi sem a\u00f0rirs\u00e6ta afarkostum. \u00deeir hertugarnir \u00e1ttu systur, ok varh\u00fan mest at r\u00e1\u00f0um, \u00fev\u00ed at h\u00fan var \u00feeira vitrust. S\u00ed\u00f0an\u00e1ttu \u00feau eintal ok \u00e6tlast fyrir, hvat af skyldi kj\u00f3sa.H\u00fan kva\u00f0 \u00feat meira r\u00e1\u00f0 at v\u00e6gjast til hans me\u00f0 skattgjaldien eiga orrostu, \"ok er \u00feat r\u00e1\u00f0 at \u00e6tla s\u00e9r h\u00f3f,en sn\u00faast \u00fe\u00e1 til m\u00f3tst\u00f6\u00f0u, er styrkr er nokkurr,\" kva\u00f0h\u00e9r sv\u00e1 mundu fara sem \u00ed \u00f6\u00f0rum st\u00f6\u00f0um, at hann munsigrast. S\u00ed\u00f0an s\u00f6g\u00f0u \u00feeir hertugarnir, at \u00feeir vilja j\u00e1tahonum skattgjaldi. Hann kva\u00f0 \u00feat forsj\u00e1ligt, ok s\u00e6ttast\u00e1 \u00feat.Hildibrandr H\u00fanakappi braut n\u00fa margar \u00fej\u00f3\u00f0irundir sik. Hann spyrr n\u00fa \u00feau t\u00ed\u00f0endi, fall Bu\u00f0la konungs,m\u00f3\u00f0urf\u00f6\u00f0ur s\u00edns. Hann stefndi \u00fe\u00e1 her at s\u00e9r afn\u00fdju ok kvaddi \u00feings. Hann m\u00e6lti, kva\u00f0 m\u00f6nnumkunnigt, hverr vandi \u00e1 var, at fara \u00ed herna\u00f0, en l\u00e9t eigiat h\u00f6gum til skipt, ef herja skyldi \u00e1 v\u00edkinga e\u00f0a \u00e1 a\u00f0ramenn fyrir litla s\u00f6k e\u00f0a enga, en hefna eigi m\u00f3\u00f0urf\u00f6\u00f0urs\u00edns. Eptir \u00feat flutti hann herinn \u00ed r\u00edki \u00c1lfs konungsok kva\u00f0 Dani hafa kennt atf\u00f6r um b\u00fashagi. Hannl\u00e9t eisa eldum ok brenna v\u00ed\u00f0a. \u00c1lfr konungr s\u00f3tti n\u00fa\u00ed m\u00f3t me\u00f0 her sinn, ok \u00feegar \u00feeir fundust, b\u00f6r\u00f0ust\u00feeir. Hildibrandr H\u00fanakappi haf\u00f0i berserkja n\u00e1tt\u00faru,ok kom \u00e1 hann berserksgangr. Ekki var \u00c1ki hertugivi\u00f0 \u00feessa orrostu, \u00fev\u00ed at hann var \u00ed herna\u00f0i. HildibrandrH\u00fanakappi gekk \u00ed gegnum fylkingar \u00c1lfs konungs, okvar illt fyrir honum at ver\u00f0a. Hj\u00f3 hann \u00e1 tv\u00e6r hendrs\u00e9r ok s\u00f3tti grenjandi at konungsmerkinu, ok \u00ed \u00feessiorrostu fell \u00c1lfr konungr ok margt li\u00f0 hans, ok eptir\u00feat f\u00f3ru H\u00fanar aptr. Hildibrandr gerist \u00fe\u00e1 allramanna fr\u00e6gastr ok sat jafnan at b\u00faum s\u00ednum \u00e1 vetrum,en herja\u00f0i \u00e1 sumrum."}}