{"originalTitle": "Commentary_On_Beowulf_Line_1545", "author": "Not Available", "sourceLink": "http://www.perseus.tufts.edu/hopper/opensource/download", "source": "Perseus", "language": "Old_Norse", "englishTitle": "Commentary_On_Beowulf_Line_1545", "text": {"0": "hyre seax (MS. seaxe) get\u0113ah/br\u0101d [ond] br\u016bnecg. The lack of concord resulting from the retention of seaxe would not be a serious offense, see 2703 f.; note on 48. But get\u0113on, unlike gebregdan, cannot take the dat. (instr.) case. The scribal error was perhaps caused by the preceding hyre."}}