{"originalTitle": "Commentary_On_Beowulf_Lines_2137-2137", "author": "Not Available", "sourceLink": "http://www.perseus.tufts.edu/hopper/opensource/download", "source": "Perseus", "language": "Old_Norse", "englishTitle": "Commentary_On_Beowulf_Lines_2137-2137", "text": {"0": "\u00fe\u01e3r unc hw\u00efle w\u00e6s hand gem\u01e3ne. \"There to us for a while was the blendingof hands\" (W. Morris), or . . . \"battle joined\" (Sedgefield). Cp. 2473; Wulfst. 162.7 f.: \u00fe\u00e6t w\u01e3pengeewrixl weor\u00f0e gem\u01e3ne \u00feegene and \u00fer\u01e3le. The Ger. handgemein (werden) furnishes a semasiological, though not a syntactical parallel."}}