{"originalTitle": "H\u00e1lfdanar_Saga_Eysteinssonar_Chapter_1", "author": "Not Available", "sourceLink": "http://www.perseus.tufts.edu/hopper/opensource/download", "source": "Perseus", "language": "Old_Norse", "englishTitle": "H\u00e1lfdanar_Saga_Eysteinssonar_Chapter_1", "text": {"0": "\u00deR\u00c1NDR hefir konungr heitit. Vi\u00f0 hann er kenndr\u00der\u00e1ndheimr \u00ed Noregi. Hann var sonr S\u00e6mingskonungs, sonar \u00d3\u00f0ins, er r\u00e9\u00f0 fyrir H\u00e1logalandi. S\u00e6mingr\u00e1tti Naumu, er Naumudalr er vi\u00f0 kenndr. \u00der\u00e1ndrvar mikill h\u00f6f\u00f0ingi. Hans kona h\u00e9t Dagm\u00e6r, systirSvanhv\u00edtar, er Hr\u00f3mundr Gripsson \u00e1tti. \u00deeira sonr h\u00e9tEysteinn, en annarr Eirekr inn v\u00ed\u00f0f\u00f6rli, er fann \u00d3d\u00e1insakr.Hans m\u00f3\u00f0ir er ekki nefnd. Eysteinn giftist okfekk d\u00f3ttur Sigur\u00f0ar hjartar, er \u00c1sa h\u00e9t. Hennar m\u00f3\u00f0irvar \u00c1slaug, d\u00f3ttir Sigur\u00f0ar orms \u00ed auga. Eysteinn fekkme\u00f0 henni Finnm\u00f6rk ok Valdres, \u00de\u00f3tn ok Ha\u00f0aland.Hann var r\u00edkr ok stj\u00f3rnsamr. \u00deau \u00e1ttu son, er H\u00e1lfdanh\u00e9t. Hann var ok stj\u00f3rnsamr ok stilltr vel ok fr\u00ed\u00f0r s\u00fdnumok vandist snemma vi\u00f0 allar \u00ed\u00fer\u00f3ttir, \u00fe\u00e6r sem karlmannm\u00e1ttu fr\u00ed\u00f0a ok betra var at hafa en missa. Hannvar vinfastr ok tr\u00falyndr ok vinavandr, gle\u00f0ima\u00f0rmikill, sv\u00e1 at alla gle\u00f0i m\u00e1tti vi\u00f0 hann eiga, en ef honummisl\u00edka\u00f0i, \u00fe\u00e1 var hann \u00feunglyndr ok langr\u00e6kr, eneigi mj\u00f6k br\u00e1\u00f0skapa\u00f0r. Hann \u00f3x upp me\u00f0 f\u00f6\u00f0ur s\u00ednum,\u00fear til hann var fimmt\u00e1n vetra gamall. \u00de\u00e1 t\u00f3km\u00f3\u00f0ir hans s\u00f3tt ok anda\u00f0ist. \u00de\u00f3tti konungi \u00feat mikillska\u00f0i ok \u00f6llum \u00f6\u00f0rum, ok var hennar \u00fatfer\u00f0 ger\u00f0 s\u00e6miliga.Konungr undi l\u00edtt \u00ed r\u00edki s\u00ednu \u00fea\u00f0an \u00ed fr\u00e1, ok f\u00f3rhann \u00ed herna\u00f0 hvert sumar.Ma\u00f0r er nefndr Svipr. Hann var r\u00edkr b\u00f3ndi ok me\u00f0allagivins\u00e6ll. Hann \u00e1tti \u00ferj\u00e1 sonu. Einn h\u00e9t \u00dalfkell okvar kalla\u00f0r snillingr. Hann var mikill \u00f3jafna\u00f0arma\u00f0rok eigi mj\u00f6k vitr. Hann var \u00ed herna\u00f0i me\u00f0 Eysteinikonungi ok haf\u00f0i fimm skip sinna vegna. Konungr heltmikit af honum. Annarr sonr Svips h\u00e9t \u00dalfarr. Hannvar r\u00e1\u00f0gjafi konungs. Hann var vins\u00e6ll ma\u00f0r ok tr\u00falyndr,ok \u00fe\u00f3tti hann alls sta\u00f0ar b\u00e6ta til b\u00e6\u00f0i fyrir konungiok \u00f6\u00f0rum. \u00dalfr h\u00e9t inn yngsti sonr Svips. Hannvar kalla\u00f0r \u00dalfr inn illi. Hann herja\u00f0i um Eystrasaltok um Bjarmaland. Hann haf\u00f0i mikla r\u00e6ningjasveitok var all\u00f3vins\u00e6ll.Eitt sumar herja\u00f0i Eysteinn konungr \u00ed Austrveginn.\u00dalfkell snillingr var \u00fe\u00e1 me\u00f0 honum ok H\u00e1lfdan, sonrkonungs. \u00deeir h\u00f6f\u00f0u \u00ferj\u00e1 tigi skipa vel skipu\u00f0, en \u00dalfarr,br\u00f3\u00f0ir \u00dalfkels, haf\u00f0i vald yfir r\u00edki Eysteins konungs,me\u00f0an hann var \u00ed herna\u00f0inum."}}