{"originalTitle": "Ragnars_Saga_Lo\u00f0br\u00f3kar_Ok_Sona_Hans_Chapter_20", "author": "Not Available", "sourceLink": "http://www.perseus.tufts.edu/hopper/opensource/download", "source": "Perseus", "language": "Old_Norse", "englishTitle": "Ragnars_Saga_Lo\u00f0br\u00f3kar_Ok_Sona_Hans_Chapter_20", "text": {"0": "\u00d6gmundr er ma\u00f0r nefndr, er kalla\u00f0r var \u00d6gmundrinn danski. Hann f\u00f3r eitthvert sinn me\u00f0 fimm skipumok l\u00e1 vi\u00f0 S\u00e1msey \u00ed Munarv\u00e1gi. \u00de\u00e1 er \u00feat sagt, at matsveinarf\u00f3ru \u00e1 land at gera mat til, en a\u00f0rir menn f\u00f3ru \u00ed sk\u00f3gat skemmta s\u00e9r, ok \u00fear fundu \u00feeir einn tr\u00e9mann fornan,ok var fertugr at h\u00e6\u00f0 ok mosavaxinn, ok s\u00e1 \u00fe\u00f3 \u00f6ll deili\u00e1 honum, ok r\u00e6ddu n\u00fa um me\u00f0 s\u00e9r, hverr bl\u00f3tat mundihafa \u00feetta it mikla go\u00f0. Ok \u00fe\u00e1 kve\u00f0r tr\u00e9ma\u00f0rinn:\"\u00deat var fyr l\u00f6ngu,er \u00ed lei\u00f0 megirH\u00e6klings f\u00f3ruhlunnalungumfram um saltasl\u00f3\u00f0 birtinga,\u00fe\u00e1 var\u00f0k \u00feessa\u00feorps r\u00e1\u00f0andi.Ok \u00fev\u00ed settumksvar\u00f0mer\u00f0lingarsu\u00f0r hj\u00e1 salti,synir Lo\u00f0br\u00f3kar;\u00fe\u00e1 vark bl\u00f3tinntil bana m\u00f6nnum\u00ed S\u00e1mseyjusunnanver\u00f0ri.\u00dear b\u00e1\u00f0u standa,me\u00f0an str\u00f6nd \u00feolirmann hj\u00e1 \u00feyrniok mosa vaxinn;n\u00fa sk\u00fdtr \u00e1 miksk\u00fdja gr\u00e1ti,hl\u00fdr hv\u00e1rki m\u00e9rhold n\u00e9 kl\u00e6\u00f0i.\"Ok \u00feetta \u00fe\u00f3tti m\u00f6nnum undarligt ok s\u00f6g\u00f0u s\u00ed\u00f0an fr\u00e1\u00f6\u00f0rum m\u00f6nnum."}}