{"originalTitle": "Commentary_On_Beowulf_Line_2600_F", "author": "Not Available", "sourceLink": "http://www.perseus.tufts.edu/hopper/opensource/download", "source": "Perseus", "language": "Old_Norse", "englishTitle": "Commentary_On_Beowulf_Line_2600_F", "text": {"0": "sibb' \u01e3fre ne m\u00e6g/wiht onwendan. As the intrans. use of onwendan (i.e. ' change') is not authenticated, sibb isnow commonly taken as ace., and wiht as nom. Still, the possibility of construing sibb  as the subject of the clause is to be conceded; ' kinship can never change anything,' i.e. 'will always prevent a change (of heart).' For \u00fe\u0101m \u00f0e w\u0113l \u00feence\u00f0, see note on 287 ff."}}